{
  "last_sha": "5fd76df411b7ce4bd5a5f51a680f77b56195b604",
  "last_report_at": "2026-05-07T23:53:39+00:00",
  "last_report_file": "reports/Seven-Shards-ORIGIN/2026-05-07T23-51-19Z.md",
  "report_count": 16,
  "last_commit_at": "2026-05-08T01:57:47+09:00",
  "contributors": [
    "AKWLD"
  ],
  "repo_full_name": "Bit-Unity15th-MultiplayGameProjects/Seven-Shards-ORIGIN",
  "repo_id": 1216537484,
  "repo_name": "Seven-Shards-ORIGIN",
  "repo_node_id": "R_kgDOSILjjA",
  "recent_report_ats": [
    "2026-04-30T06:22:43+00:00",
    "2026-04-30T10:30:41+00:00",
    "2026-05-01T08:55:35+00:00",
    "2026-05-01T14:08:55+00:00",
    "2026-05-04T08:14:32+00:00",
    "2026-05-06T04:05:03+00:00",
    "2026-05-06T09:16:06+00:00",
    "2026-05-07T03:23:48+00:00",
    "2026-05-07T23:53:39+00:00"
  ]
}
